MANIFEST.in
readme.md
setup.py
pycsal/PCM.py
pycsal/__init__.py
pycsal/analysis.py
pycsal/class.py
pycsal/deepmd.calculator.py
pycsal/final.py
pycsal/ga.py
pycsal/gen_randSpg.py
pycsal/gen_stru.py
pycsal/init.py
pycsal/interface_deepmd.py
pycsal/interface_reann.py
pycsal/main.py
pycsal/opt.py
pycsal/pick.py
pycsal/reann.py
pycsal/tool.py
pycsal.egg-info/PKG-INFO
pycsal.egg-info/SOURCES.txt
pycsal.egg-info/dependency_links.txt
pycsal.egg-info/requires.txt
pycsal.egg-info/top_level.txt
test/test_ga.py
test/test_pyxtal.py