Metadata-Version: 2.1
Name: pycsal
Version: 0.0.2
Summary: Python crystal search with active learning (pycsal)
Home-page: https://github.com/phys-chem/pycsal/
Author: Jialu Chen
Author-email: jialu.chen@ist.ac.at
Classifier: Programming Language :: Python :: 3
Classifier: License :: OSI Approved :: MIT License
Classifier: Operating System :: OS Independent
Requires-Python: >=3.7
